odoo/addons/repair_type_product_destination/README.rst
odoo/addons/repair_type_product_destination/__init__.py
odoo/addons/repair_type_product_destination/__manifest__.py
odoo/addons/repair_type_product_destination/i18n/ca.po
odoo/addons/repair_type_product_destination/i18n/es.po
odoo/addons/repair_type_product_destination/i18n/it.po
odoo/addons/repair_type_product_destination/i18n/repair_type_product_destination.pot
odoo/addons/repair_type_product_destination/models/__init__.py
odoo/addons/repair_type_product_destination/models/repair.py
odoo/addons/repair_type_product_destination/models/stock_picking_type.py
odoo/addons/repair_type_product_destination/readme/CONTRIBUTORS.md
odoo/addons/repair_type_product_destination/readme/DESCRIPTION.md
odoo/addons/repair_type_product_destination/readme/USAGE.md
odoo/addons/repair_type_product_destination/static/description/icon.png
odoo/addons/repair_type_product_destination/static/description/index.html
odoo/addons/repair_type_product_destination/tests/__init__.py
odoo/addons/repair_type_product_destination/tests/test_repair_type_product_destination.py
odoo/addons/repair_type_product_destination/views/repair_views.xml
odoo/addons/repair_type_product_destination/views/stock_picking_type_views.xml
odoo_addon_repair_type_product_destination-18.0.1.0.0.2.dist-info/METADATA
odoo_addon_repair_type_product_destination-18.0.1.0.0.2.dist-info/WHEEL
odoo_addon_repair_type_product_destination-18.0.1.0.0.2.dist-info/top_level.txt
odoo_addon_repair_type_product_destination-18.0.1.0.0.2.dist-info/RECORD
